pybuildkite/__init__.py
pybuildkite/access_tokens.py
pybuildkite/agents.py
pybuildkite/annotations.py
pybuildkite/artifacts.py
pybuildkite/buildkite.py
pybuildkite/builds.py
pybuildkite/client.py
pybuildkite/decorators.py
pybuildkite/emojis.py
pybuildkite/exceptions.py
pybuildkite/jobs.py
pybuildkite/meta.py
pybuildkite/organizations.py
pybuildkite/pipelines.py
pybuildkite/teams.py
pybuildkite/users.py
pybuildkite-1.3.0.dist-info/licenses/LICENSE
pybuildkite-1.3.0.dist-info/METADATA
pybuildkite-1.3.0.dist-info/WHEEL
pybuildkite-1.3.0.dist-info/top_level.txt
pybuildkite-1.3.0.dist-info/RECORD
