Metadata-Version: 2.4
Name: pybuildkite
Version: 1.3.0
Summary: Python wrapper for the Buildkite API
Home-page: https://github.com/pyasi/pybuildkite
Download-URL: https://github.com/pyasi/pybuildkite/archive/master.zip
Author: Peter Yasi
License: BSD 2-Clause License
Project-URL: Homepage, https://github.com/pyasi/pybuildkite
Project-URL: Repository, https://github.com/pyasi/pybuildkite.git
Project-URL: Download, https://github.com/pyasi/pybuildkite/archive/master.zip
Keywords: Buildkite,Continuous Integration,API,CI,wrapper,python
License-File: LICENSE
Requires-Dist: requests>=2.32.2
Provides-Extra: dev
Requires-Dist: black==22.6.0; extra == "dev"
Requires-Dist: coveralls==3.3.1; extra == "dev"
Requires-Dist: mypy==1.3.0; extra == "dev"
Requires-Dist: pytest==7.3.2; extra == "dev"
Requires-Dist: pytest-cov; extra == "dev"
Dynamic: download-url
Dynamic: home-page
Dynamic: license-file
